replacy/__init__.py
replacy/db.py
replacy/default_match_hooks.py
replacy/default_scorer.py
replacy/filter_0distance.py
replacy/filter_spans_by_cat.py
replacy/inflector.py
replacy/ref_matcher.py
replacy/resources/forms_lookup.json
replacy/resources/match_dict.json
replacy/resources/match_dict_schema.json
replacy/resources/patterns_test_data.json
replacy/resources/test.arpa
replacy/scorer.py
replacy/suggestion.py
replacy/suggestion_joiner.py
replacy/test_helper.py
replacy/util.py
replacy/version.py
replacy-3.7.2.dist-info/LICENSE.md
replacy-3.7.2.dist-info/WHEEL
replacy-3.7.2.dist-info/METADATA
replacy-3.7.2.dist-info/RECORD
