Metadata-Version: 2.1
Name: replacy
Version: 3.7.2
Summary: ReplaCy = spaCy Matcher + pyInflect. Create rules, correct sentences.
License: MIT
Author: melisa-writer
Author-email: melisa@writer.com
Requires-Python: >=3.6,<4.0
Classifier: License :: OSI Approved :: MIT License
Classifier: Programming Language :: Python :: 3
Classifier: Programming Language :: Python :: 3.10
Classifier: Programming Language :: Python :: 3.6
Classifier: Programming Language :: Python :: 3.7
Classifier: Programming Language :: Python :: 3.8
Classifier: Programming Language :: Python :: 3.9
Requires-Dist: jsonschema (>=2.6.0,<3.0.0)
Requires-Dist: lemminflect (==0.2.1)
Requires-Dist: pyfunctional (>=1.2.0,<2.0.0)
